flask_lazyapi.py
setup.py
flask_lazyapi.egg-info/PKG-INFO
flask_lazyapi.egg-info/SOURCES.txt
flask_lazyapi.egg-info/dependency_links.txt
flask_lazyapi.egg-info/requires.txt
flask_lazyapi.egg-info/top_level.txt